rtl/memory.sv
`default_nettype none

module memory (
    input  logic        clock,
    input  logic [31:0] addr_1,
    input  logic [31:0] din_1,
    output logic [31:0] dout_1,
    input  logic        en_1,
    input  logic        we_1,
    input  logic [31:0] addr_2,
    input  logic [31:0] din_2,
    output logic [31:0] dout_2,
    input  logic        en_2,
    input  logic        we_2
);

  memory_simulation u_memory (.*);

endmodule : memory


/*
  Clka and Clkb should both be the same shared clock
  ena and enb enable any memory accesses
  wea and web are read when 0 and write when 1
 */
// module blk_memory (
//   input  logic         clka,
//   input  logic         ena,
//   input  logic         wea,            // 1-bit write enable for port A
//   input  logic [13:0]  addra,          // 14-bit address for port A
//   input  logic [31:0]  dina,           // 32-bit data input for port A
//   output logic [31:0]  douta,          // 32-bit data output for port A
//   input  logic         clkb,
//   input  logic         enb,
//   input  logic         web,            // 1-bit write enable for port B
//   input  logic [13:0]  addrb,          // 14-bit address for port B
//   input  logic [31:0]  dinb,           // 32-bit data input for port B
//   output logic [31:0]  doutb           // 32-bit data output for port B
// );
// 
//   blk_mem_wrapper block_memory_wrapper(.*);
// 
// endmodule: blk_memory

module memory_simulation (
  input  logic        clock,
  input  logic [31:0] addr_1,
  input  logic [31:0] din_1,
  output logic [31:0] dout_1,
  input  logic        en_1,
  input  logic        we_1,
  input  logic [31:0] addr_2,
  input  logic [31:0] din_2,
  output logic [31:0] dout_2,
  input  logic        en_2,
  input  logic        we_2
);

  parameter int SIM_MEM_SIZE = 1000;

  logic [31:0] mem[SIM_MEM_SIZE];

  logic [31:0] dout_temp_1, dout_temp_2;
  
  always_ff @(posedge clock) begin
      if (en_1 && !we_1) dout_temp_1 <= mem[addr_1];
      if (en_2 && !we_2) dout_temp_2 <= mem[addr_2];

      dout_1 <= dout_temp_1;
      dout_2 <= dout_temp_2;
  end

  always_ff @(posedge clock) begin
    if (en_1 && we_1) mem[addr_1] <= din_1;
    if (en_2 && we_2) mem[addr_2] <= din_2;
  end

  initial begin
    // static int fd = $fopen("memory.hex", "r");
    // static int status;
    // static logic [$clog2(SIM_MEM_SIZE+1):0] addr;
    // static logic [31:0] mem_line;
    // if (fd) begin
    //   addr = '0;
    //   while (!$feof(
    //       fd
    //   )) begin
    //     status = $fscanf(fd, "%h", mem_line);
    //     if (status == 1) begin
    //       mem[{addr, 2'b00}] = mem_line;
    //       addr += 1;
    //     end
    //   end
    // end else begin
    //   $display("File not found");
    //   $fflush();
    //   $finish(2);
    // end

    // $fclose(fd);

    $readmemh("memory.hex", mem);
  end

endmodule : memory_simulation

rtl/uniprocessor.sv
`default_nettype none

module uniprocessor(
    input logic clock,
    input logic rst
);

    logic [31:0] addr_1, data_1_in, data_1_out;
    logic        we_1;

    logic [31:0] addr_2, data_2_out, data_2_in;
  
    logic lte_zero;

    logic       sel_addr_1;
    logic [1:0] sel_addr_2;

    logic sel_PC, en_PC;

    logic en_A, en_B, en_B_addr;

    procFSM fsm(.clock(clock),
                .rst(rst),
                .lte_zero(lte_zero),
                .we_1(we_1),
                .en_A(en_A),
                .en_B(en_B),
                .en_B_addr(en_B_addr),
                .sel_addr_1(sel_addr_1),
                .sel_addr_2(sel_addr_2),
                .sel_PC(sel_PC),
                .en_PC(en_PC)
    );

    memory u_memory (
        .clock(clock),
        .addr_1(addr_1),
        .din_1(data_1_in),
        .dout_1(data_1_out),
        .we_1(we_1),
        .addr_2(addr_2),
        .din_2(data_2_in),
        .dout_2(data_2_out),
        .en_1(1'b1),
        .en_2(1'b1),
        .we_2(1'b0)
    );
    
    logic [31:0] PC_in, PC_out;

    assign PC_in = (sel_PC) ? data_2_out : (PC_out + 3);
    
    always_ff @(posedge clock, posedge rst) begin
        if (rst)
            PC_out <= 32'b0;
        else if (en_PC)
            PC_out <= PC_in;
        else
            PC_out <= PC_out;
    end
    
    logic [31:0] reg_A_out, reg_B_out, reg_B_addr_out;

    always_comb begin
        if (!sel_addr_1) begin
            addr_1 = PC_out + 1;
        end else begin
            addr_1 = reg_B_addr_out;
        end

        case (sel_addr_2)
            2'b00: addr_2 = PC_out;
            2'b01: addr_2 = data_2_out;
            2'b10: addr_2 = PC_out + 2;
            default: addr_2 = PC_out;
        endcase
    end

    always_ff @(posedge clock, posedge rst) begin
        if (rst) begin
            reg_A_out      <= '0;
            reg_B_out      <= '0;
            reg_B_addr_out <= '0;
        end
        else begin
            if (en_A) begin
                reg_A_out <= data_2_out;
            end
            if (en_B) begin
                reg_B_out <= data_1_out;
            end
            if (en_B_addr) begin
                reg_B_addr_out <= data_1_out;
            end
        end
    end

    logic signed [31:0] B_minus_A;

    assign B_minus_A = reg_B_out - reg_A_out;
    assign lte_zero = B_minus_A <= 0;

    assign data_1_in = B_minus_A;
  
endmodule: uniprocessor

module procFSM(
    input logic  clock, rst,
    input logic  lte_zero,
    output logic we_1, 
    output logic en_A, en_B, en_B_addr,
    output logic sel_addr_1,
    output logic [1:0] sel_addr_2,
    output logic sel_PC, en_PC);

    enum logic [2:0] {ADDR_AB, WAIT_READ1, LATCH_B_ADDR, DATA_AB, WAIT_READ2, LATCH_DATA_AB, WAIT_READ3, WRITE_BACK} 
        curr_state, next_state;

    always_comb begin
        we_1 = 1'b0;
        en_A = 1'b0;
        en_B = 1'b0;
        en_B_addr  = 1'b0;
        sel_addr_1 = 2'd0;
        sel_addr_2 = 1'b0;
        sel_PC = 1'b0;
        en_PC = 1'b0;
        case(curr_state)
            ADDR_AB: begin
                sel_addr_2 = 2'd0;
                sel_addr_1 = 1'b0;
                next_state = WAIT_READ1;
            end
            WAIT_READ1: begin
                next_state = LATCH_B_ADDR;
            end
            LATCH_B_ADDR: begin
                en_B_addr = 1'b1;
                next_state = DATA_AB;
            end
            DATA_AB: begin
                sel_addr_2 = 2'd1;
                sel_addr_1 = 1'b1;
                next_state = WAIT_READ2;
            end
            WAIT_READ2: begin
                next_state = LATCH_DATA_AB;
            end
            LATCH_DATA_AB: begin
                en_A = 1'b1;
                en_B = 1'b1;
                sel_addr_2 = 2'd2;
                next_state = WAIT_READ3;
            end
            WAIT_READ3: begin
                next_state = WRITE_BACK;
            end
            WRITE_BACK: begin
                we_1 = 1'b1;
                sel_PC = lte_zero;
                en_PC = 1'b1;
                sel_addr_1 = 1'b1;
                next_state = ADDR_AB;
            end
        endcase
    end

    always_ff @(posedge clock, posedge rst) begin
        if (rst)
            curr_state <= ADDR_AB;
        else
            curr_state <= next_state;
    end

endmodule: procFSM

tb/tb.sv
`default_nettype none

module tb ();

  logic clock;
  logic rst;

  uniprocessor DUT (.*);

  initial begin
    $dumpfile("tb.vcd");
    $dumpvars(0,tb);
  end

  initial begin
    clock = 0;
    forever #1 clock <= ~clock;
  end

  initial begin
    rst <= 1;
    @(posedge clock);
    rst <= 0;

    for (int i = 0; i < 1000; i++) begin
      @(posedge clock);
    end

    $finish;
  end

endmodule : tb

tb.vcd
$date
	Sat Jan 18 15:09:31 2025
$end
$version
	Icarus Verilog
$end
$timescale
	1s
$end
$scope module tb $end
$var reg 1 ! clock $end
$var reg 1 " rst $end
$scope module DUT $end
$var wire 1 ! clock $end
$var wire 32 # data_1_in [31:0] $end
$var wire 1 " rst $end
$var wire 1 $ we_1 $end
$var wire 2 % sel_addr_2 [1:0] $end
$var wire 1 & sel_addr_1 $end
$var wire 1 ' sel_PC $end
$var wire 1 ( lte_zero $end
$var wire 1 ) en_PC $end
$var wire 1 * en_B_addr $end
$var wire 1 + en_B $end
$var wire 1 , en_A $end
$var wire 32 - data_2_out [31:0] $end
$var wire 32 . data_1_out [31:0] $end
$var wire 32 / PC_in [31:0] $end
$var wire 32 0 B_minus_A [31:0] $end
$var reg 32 1 PC_out [31:0] $end
$var reg 32 2 addr_1 [31:0] $end
$var reg 32 3 addr_2 [31:0] $end
$var reg 32 4 data_2_in [31:0] $end
$var reg 32 5 reg_A_out [31:0] $end
$var reg 32 6 reg_B_addr_out [31:0] $end
$var reg 32 7 reg_B_out [31:0] $end
$scope module fsm $end
$var wire 1 ! clock $end
$var wire 1 ( lte_zero $end
$var wire 1 " rst $end
$var reg 3 8 curr_state [2:0] $end
$var reg 1 , en_A $end
$var reg 1 + en_B $end
$var reg 1 * en_B_addr $end
$var reg 1 ) en_PC $end
$var reg 3 9 next_state [2:0] $end
$var reg 1 ' sel_PC $end
$var reg 1 & sel_addr_1 $end
$var reg 2 : sel_addr_2 [1:0] $end
$var reg 1 $ we_1 $end
$upscope $end
$scope module u_memory $end
$var wire 32 ; addr_1 [31:0] $end
$var wire 32 < addr_2 [31:0] $end
$var wire 1 ! clock $end
$var wire 32 = din_1 [31:0] $end
$var wire 32 > din_2 [31:0] $end
$var wire 1 ? en_1 $end
$var wire 1 @ en_2 $end
$var wire 1 $ we_1 $end
$var wire 1 A we_2 $end
$var wire 32 B dout_2 [31:0] $end
$var wire 32 C dout_1 [31:0] $end
$scope module u_memory $end
$var wire 32 D addr_1 [31:0] $end
$var wire 32 E addr_2 [31:0] $end
$var wire 1 ! clock $end
$var wire 32 F din_1 [31:0] $end
$var wire 32 G din_2 [31:0] $end
$var wire 1 ? en_1 $end
$var wire 1 @ en_2 $end
$var wire 1 $ we_1 $end
$var wire 1 A we_2 $end
$var parameter 32 H SIM_MEM_SIZE $end
$var reg 32 I dout_1 [31:0] $end
$var reg 32 J dout_2 [31:0] $end
$var reg 32 K dout_temp_1 [31:0] $end
$var reg 32 L dout_temp_2 [31:0] $end
$upscope $end
$upscope $end
$upscope $end
$scope begin $ivl_for_loop0 $end
$var integer 32 M i [31:0] $end
$upscope $end
$upscope $end
$enddefinitions $end
$comment Show the parameter values. $end
$dumpall
b1111101000 H
$end
#0
$dumpvars
b0 M
bx L
bx K
bx J
bx I
bx G
b0 F
b0 E
b1 D
bx C
bx B
0A
1@
1?
bx >
b0 =
b0 <
b1 ;
b0 :
b1 9
b0 8
b0 7
b0 6
b0 5
bx 4
b0 3
b1 2
b0 1
b0 0
b11 /
bx .
bx -
0,
0+
0*
0)
1(
0'
0&
b0 %
0$
b0 #
1"
0!
$end
#1
b11 L
b100 K
0"
1!
#2
0!
#3
b10 9
b1 8
b11 -
b11 B
b11 J
b100 .
b100 C
b100 I
b1 M
1!
#4
0!
#5
b11 9
1*
b10 8
b10 M
1!
#6
0!
#7
b11 3
b11 <
b11 E
b100 2
b100 ;
b100 D
b100 9
1&
b1 %
b1 :
0*
b11 8
b100 6
b11 M
1!
#8
0!
#9
b0 3
b0 <
b0 E
b1 2
b1 ;
b1 D
b101 9
b0 %
b0 :
0&
b100 8
b111 L
b111 K
b100 M
1!
#10
0!
#11
b10 3
b10 <
b10 E
b110 9
b10 %
b10 :
1+
1,
b101 8
b111 -
b111 B
b111 J
b111 .
b111 C
b111 I
b11 L
b100 K
b101 M
1!
#12
0!
#13
b0 3
b0 <
b0 E
b111 9
b0 %
b0 :
0+
0,
b111 7
b0 #
b0 =
b0 F
b0 0
b111 5
b110 8
b11 -
b11 B
b11 J
b100 .
b100 C
b100 I
b110 L
b110 M
1!
#14
0!
#15
b100 2
b100 ;
b100 D
b110 /
b0 9
1&
1)
1'
1$
b111 8
b110 -
b110 B
b110 J
b11 L
b111 M
1!
#16
0!
#17
b111 2
b111 ;
b111 D
b1 9
0)
0'
0&
0$
b1001 /
b110 3
b110 <
b110 E
b110 1
b0 8
b11 -
b11 B
b11 J
b1000 M
1!
#18
0!
#19
b10 9
b1 8
b1001 M
1!
#20
0!
#21
b11 9
1*
b10 8
b1010 M
1!
#22
0!
#23
b11 3
b11 <
b11 E
b100 2
b100 ;
b100 D
b100 9
1&
b1 %
b1 :
0*
b11 8
b1011 M
1!
#24
0!
#25
b110 3
b110 <
b110 E
b111 2
b111 ;
b111 D
b101 9
b0 %
b0 :
0&
b100 8
b111 L
b0 K
b1100 M
1!
#26
0!
#27
b1000 3
b1000 <
b1000 E
b110 9
b10 %
b10 :
1+
1,
b101 8
b111 -
b111 B
b111 J
b0 .
b0 C
b0 I
b11 L
b100 K
b1101 M
1!
#28
0!
#29
b110 3
b110 <
b110 E
b111 9
b0 %
b0 :
0+
0,
b11111111111111111111111111111001 #
b11111111111111111111111111111001 =
b11111111111111111111111111111001 F
b11111111111111111111111111111001 0
b0 7
b110 8
b11 -
b11 B
b11 J
b100 .
b100 C
b100 I
b0 L
b1110 M
1!
#30
0!
#31
b100 2
b100 ;
b100 D
b0 /
b0 9
1&
1)
1'
1$
b111 8
b0 -
b0 B
b0 J
b11 L
b1111 M
1!
#32
0!
#33
b1 2
b1 ;
b1 D
b1 9
0)
0'
0&
0$
b11 /
b0 3
b0 <
b0 E
b0 1
b0 8
b11 -
b11 B
b11 J
b10000 M
1!
#34
0!
#35
b10 9
b1 8
b10001 M
1!
#36
0!
#37
b11 9
1*
b10 8
b10010 M
1!
#38
0!
#39
b11 3
b11 <
b11 E
b100 2
b100 ;
b100 D
b100 9
1&
b1 %
b1 :
0*
b11 8
b10011 M
1!
#40
0!
#41
b0 3
b0 <
b0 E
b1 2
b1 ;
b1 D
b101 9
b0 %
b0 :
0&
b100 8
b111 L
b11111111111111111111111111111001 K
b10100 M
1!
#42
0!
#43
b10 3
b10 <
b10 E
b110 9
b10 %
b10 :
1+
1,
b101 8
b111 -
b111 B
b111 J
b11111111111111111111111111111001 .
b11111111111111111111111111111001 C
b11111111111111111111111111111001 I
b11 L
b100 K
b10101 M
1!
#44
0!
#45
b0 3
b0 <
b0 E
b111 9
b0 %
b0 :
0+
0,
b11111111111111111111111111110010 #
b11111111111111111111111111110010 =
b11111111111111111111111111110010 F
b11111111111111111111111111110010 0
b11111111111111111111111111111001 7
b110 8
b11 -
b11 B
b11 J
b100 .
b100 C
b100 I
b110 L
b10110 M
1!
#46
0!
#47
b100 2
b100 ;
b100 D
b110 /
b0 9
1&
1)
1'
1$
b111 8
b110 -
b110 B
b110 J
b11 L
b10111 M
1!
#48
0!
#49
b111 2
b111 ;
b111 D
b1 9
0)
0'
0&
0$
b1001 /
b110 3
b110 <
b110 E
b110 1
b0 8
b11 -
b11 B
b11 J
b11000 M
1!
#50
0!
#51
b10 9
b1 8
b11001 M
1!
#52
0!
#53
b11 9
1*
b10 8
b11010 M
1!
#54
0!
#55
b11 3
b11 <
b11 E
b100 2
b100 ;
b100 D
b100 9
1&
b1 %
b1 :
0*
b11 8
b11011 M
1!
#56
0!
#57
b110 3
b110 <
b110 E
b111 2
b111 ;
b111 D
b101 9
b0 %
b0 :
0&
b100 8
b111 L
b11111111111111111111111111110010 K
b11100 M
1!
#58
0!
#59
b1000 3
b1000 <
b1000 E
b110 9
b10 %
b10 :
1+
1,
b101 8
b111 -
b111 B
b111 J
b11111111111111111111111111110010 .
b11111111111111111111111111110010 C
b11111111111111111111111111110010 I
b11 L
b100 K
b11101 M
1!
#60
0!
#61
b110 3
b110 <
b110 E
b111 9
b0 %
b0 :
0+
0,
b11111111111111111111111111101011 #
b11111111111111111111111111101011 =
b11111111111111111111111111101011 F
b11111111111111111111111111101011 0
b11111111111111111111111111110010 7
b110 8
b11 -
b11 B
b11 J
b100 .
b100 C
b100 I
b0 L
b11110 M
1!
#62
0!
#63
b100 2
b100 ;
b100 D
b0 /
b0 9
1&
1)
1'
1$
b111 8
b0 -
b0 B
b0 J
b11 L
b11111 M
1!
#64
0!
#65
b1 2
b1 ;
b1 D
b1 9
0)
0'
0&
0$
b11 /
b0 3
b0 <
b0 E
b0 1
b0 8
b11 -
b11 B
b11 J
b100000 M
1!
#66
0!
#67
b10 9
b1 8
b100001 M
1!
#68
0!
#69
b11 9
1*
b10 8
b100010 M
1!
#70
0!
#71
b11 3
b11 <
b11 E
b100 2
b100 ;
b100 D
b100 9
1&
b1 %
b1 :
0*
b11 8
b100011 M
1!
#72
0!
#73
b0 3
b0 <
b0 E
b1 2
b1 ;
b1 D
b101 9
b0 %
b0 :
0&
b100 8
b111 L
b11111111111111111111111111101011 K
b100100 M
1!
#74
0!
#75
b10 3
b10 <
b10 E
b110 9
b10 %
b10 :
1+
1,
b101 8
b111 -
b111 B
b111 J
b11111111111111111111111111101011 .
b11111111111111111111111111101011 C
b11111111111111111111111111101011 I
b11 L
b100 K
b100101 M
1!
#76
0!
#77
b0 3
b0 <
b0 E
b111 9
b0 %
b0 :
0+
0,
b11111111111111111111111111100100 #
b11111111111111111111111111100100 =
b11111111111111111111111111100100 F
b11111111111111111111111111100100 0
b11111111111111111111111111101011 7
b110 8
b11 -
b11 B
b11 J
b100 .
b100 C
b100 I
b110 L
b100110 M
1!
#78
0!
#79
b100 2
b100 ;
b100 D
b110 /
b0 9
1&
1)
1'
1$
b111 8
b110 -
b110 B
b110 J
b11 L
b100111 M
1!
#80
0!
#81
b111 2
b111 ;
b111 D
b1 9
0)
0'
0&
0$
b1001 /
b110 3
b110 <
b110 E
b110 1
b0 8
b11 -
b11 B
b11 J
b101000 M
1!
#82
0!
#83
b10 9
b1 8
b101001 M
1!
#84
0!
#85
b11 9
1*
b10 8
b101010 M
1!
#86
0!
#87
b11 3
b11 <
b11 E
b100 2
b100 ;
b100 D
b100 9
1&
b1 %
b1 :
0*
b11 8
b101011 M
1!
#88
0!
#89
b110 3
b110 <
b110 E
b111 2
b111 ;
b111 D
b101 9
b0 %
b0 :
0&
b100 8
b111 L
b11111111111111111111111111100100 K
b101100 M
1!
#90
0!
#91
b1000 3
b1000 <
b1000 E
b110 9
b10 %
b10 :
1+
1,
b101 8
b111 -
b111 B
b111 J
b11111111111111111111111111100100 .
b11111111111111111111111111100100 C
b11111111111111111111111111100100 I
b11 L
b100 K
b101101 M
1!
#92
0!
#93
b110 3
b110 <
b110 E
b111 9
b0 %
b0 :
0+
0,
b11111111111111111111111111011101 #
b11111111111111111111111111011101 =
b11111111111111111111111111011101 F
b11111111111111111111111111011101 0
b11111111111111111111111111100100 7
b110 8
b11 -
b11 B
b11 J
b100 .
b100 C
b100 I
b0 L
b101110 M
1!
#94
0!
#95
b100 2
b100 ;
b100 D
b0 /
b0 9
1&
1)
1'
1$
b111 8
b0 -
b0 B
b0 J
b11 L
b101111 M
1!
#96
0!
#97
b1 2
b1 ;
b1 D
b1 9
0)
0'
0&
0$
b11 /
b0 3
b0 <
b0 E
b0 1
b0 8
b11 -
b11 B
b11 J
b110000 M
1!
#98
0!
#99
b10 9
b1 8
b110001 M
1!
#100
0!
#101
b11 9
1*
b10 8
b110010 M
1!
#102
0!
#103
b11 3
b11 <
b11 E
b100 2
b100 ;
b100 D
b100 9
1&
b1 %
b1 :
0*
b11 8
b110011 M
1!
#104
0!
#105
b0 3
b0 <
b0 E
b1 2
b1 ;
b1 D
b101 9
b0 %
b0 :
0&
b100 8
b111 L
b11111111111111111111111111011101 K
b110100 M
1!
#106
0!
#107
b10 3
b10 <
b10 E
b110 9
b10 %
b10 :
1+
1,
b101 8
b111 -
b111 B
b111 J
b11111111111111111111111111011101 .
b11111111111111111111111111011101 C
b11111111111111111111111111011101 I
b11 L
b100 K
b110101 M
1!
#108
0!
#109
b0 3
b0 <
b0 E
b111 9
b0 %
b0 :
0+
0,
b11111111111111111111111111010110 #
b11111111111111111111111111010110 =
b11111111111111111111111111010110 F
b11111111111111111111111111010110 0
b11111111111111111111111111011101 7
b110 8
b11 -
b11 B
b11 J
b100 .
b100 C
b100 I
b110 L
b110110 M
1!
#110
0!
#111
b100 2
b100 ;
b100 D
b110 /
b0 9
1&
1)
1'
1$
b111 8
b110 -
b110 B
b110 J
b11 L
b110111 M
1!
#112
0!
#113
b111 2
b111 ;
b111 D
b1 9
0)
0'
0&
0$
b1001 /
b110 3
b110 <
b110 E
b110 1
b0 8
b11 -
b11 B
b11 J
b111000 M
1!
#114
0!
#115
b10 9
b1 8
b111001 M
1!
#116
0!
#117
b11 9
1*
b10 8
b111010 M
1!
#118
0!
#119
b11 3
b11 <
b11 E
b100 2
b100 ;
b100 D
b100 9
1&
b1 %
b1 :
0*
b11 8
b111011 M
1!
#120
0!
#121
b110 3
b110 <
b110 E
b111 2
b111 ;
b111 D
b101 9
b0 %
b0 :
0&
b100 8
b111 L
b11111111111111111111111111010110 K
b111100 M
1!
#122
0!
#123
b1000 3
b1000 <
b1000 E
b110 9
b10 %
b10 :
1+
1,
b101 8
b111 -
b111 B
b111 J
b11111111111111111111111111010110 .
b11111111111111111111111111010110 C
b11111111111111111111111111010110 I
b11 L
b100 K
b111101 M
1!
#124
0!
#125
b110 3
b110 <
b110 E
b111 9
b0 %
b0 :
0+
0,
b11111111111111111111111111001111 #
b11111111111111111111111111001111 =
b11111111111111111111111111001111 F
b11111111111111111111111111001111 0
b11111111111111111111111111010110 7
b110 8
b11 -
b11 B
b11 J
b100 .
b100 C
b100 I
b0 L
b111110 M
1!
#126
0!
#127
b100 2
b100 ;
b100 D
b0 /
b0 9
1&
1)
1'
1$
b111 8
b0 -
b0 B
b0 J
b11 L
b111111 M
1!
#128
0!
#129
b1 2
b1 ;
b1 D
b1 9
0)
0'
0&
0$
b11 /
b0 3
b0 <
b0 E
b0 1
b0 8
b11 -
b11 B
b11 J
b1000000 M
1!
#130
0!
#131
b10 9
b1 8
b1000001 M
1!
#132
0!
#133
b11 9
1*
b10 8
b1000010 M
1!
#134
0!
#135
b11 3
b11 <
b11 E
b100 2
b100 ;
b100 D
b100 9
1&
b1 %
b1 :
0*
b11 8
b1000011 M
1!
#136
0!
#137
b0 3
b0 <
b0 E
b1 2
b1 ;
b1 D
b101 9
b0 %
b0 :
0&
b100 8
b111 L
b11111111111111111111111111001111 K
b1000100 M
1!
#138
0!
#139
b10 3
b10 <
b10 E
b110 9
b10 %
b10 :
1+
1,
b101 8
b111 -
b111 B
b111 J
b11111111111111111111111111001111 .
b11111111111111111111111111001111 C
b11111111111111111111111111001111 I
b11 L
b100 K
b1000101 M
1!
#140
0!
#141
b0 3
b0 <
b0 E
b111 9
b0 %
b0 :
0+
0,
b11111111111111111111111111001000 #
b11111111111111111111111111001000 =
b11111111111111111111111111001000 F
b11111111111111111111111111001000 0
b11111111111111111111111111001111 7
b110 8
b11 -
b11 B
b11 J
b100 .
b100 C
b100 I
b110 L
b1000110 M
1!
#142
0!
#143
b100 2
b100 ;
b100 D
b110 /
b0 9
1&
1)
1'
1$
b111 8
b110 -
b110 B
b110 J
b11 L
b1000111 M
1!
#144
0!
#145
b111 2
b111 ;
b111 D
b1 9
0)
0'
0&
0$
b1001 /
b110 3
b110 <
b110 E
b110 1
b0 8
b11 -
b11 B
b11 J
b1001000 M
1!
#146
0!
#147
b10 9
b1 8
b1001001 M
1!
#148
0!
#149
b11 9
1*
b10 8
b1001010 M
1!
#150
0!
#151
b11 3
b11 <
b11 E
b100 2
b100 ;
b100 D
b100 9
1&
b1 %
b1 :
0*
b11 8
b1001011 M
1!
#152
0!
#153
b110 3
b110 <
b110 E
b111 2
b111 ;
b111 D
b101 9
b0 %
b0 :
0&
b100 8
b111 L
b11111111111111111111111111001000 K
b1001100 M
1!
#154
0!
#155
b1000 3
b1000 <
b1000 E
b110 9
b10 %
b10 :
1+
1,
b101 8
b111 -
b111 B
b111 J
b11111111111111111111111111001000 .
b11111111111111111111111111001000 C
b11111111111111111111111111001000 I
b11 L
b100 K
b1001101 M
1!
#156
0!
#157
b110 3
b110 <
b110 E
b111 9
b0 %
b0 :
0+
0,
b11111111111111111111111111000001 #
b11111111111111111111111111000001 =
b11111111111111111111111111000001 F
b11111111111111111111111111000001 0
b11111111111111111111111111001000 7
b110 8
b11 -
b11 B
b11 J
b100 .
b100 C
b100 I
b0 L
b1001110 M
1!
#158
0!
#159
b100 2
b100 ;
b100 D
b0 /
b0 9
1&
1)
1'
1$
b111 8
b0 -
b0 B
b0 J
b11 L
b1001111 M
1!
#160
0!
#161
b1 2
b1 ;
b1 D
b1 9
0)
0'
0&
0$
b11 /
b0 3
b0 <
b0 E
b0 1
b0 8
b11 -
b11 B
b11 J
b1010000 M
1!
#162
0!
#163
b10 9
b1 8
b1010001 M
1!
#164
0!
#165
b11 9
1*
b10 8
b1010010 M
1!
#166
0!
#167
b11 3
b11 <
b11 E
b100 2
b100 ;
b100 D
b100 9
1&
b1 %
b1 :
0*
b11 8
b1010011 M
1!
#168
0!
#169
b0 3
b0 <
b0 E
b1 2
b1 ;
b1 D
b101 9
b0 %
b0 :
0&
b100 8
b111 L
b11111111111111111111111111000001 K
b1010100 M
1!
#170
0!
#171
b10 3
b10 <
b10 E
b110 9
b10 %
b10 :
1+
1,
b101 8
b111 -
b111 B
b111 J
b11111111111111111111111111000001 .
b11111111111111111111111111000001 C
b11111111111111111111111111000001 I
b11 L
b100 K
b1010101 M
1!
#172
0!
#173
b0 3
b0 <
b0 E
b111 9
b0 %
b0 :
0+
0,
b11111111111111111111111110111010 #
b11111111111111111111111110111010 =
b11111111111111111111111110111010 F
b11111111111111111111111110111010 0
b11111111111111111111111111000001 7
b110 8
b11 -
b11 B
b11 J
b100 .
b100 C
b100 I
b110 L
b1010110 M
1!
#174
0!
#175
b100 2
b100 ;
b100 D
b110 /
b0 9
1&
1)
1'
1$
b111 8
b110 -
b110 B
b110 J
b11 L
b1010111 M
1!
#176
0!
#177
b111 2
b111 ;
b111 D
b1 9
0)
0'
0&
0$
b1001 /
b110 3
b110 <
b110 E
b110 1
b0 8
b11 -
b11 B
b11 J
b1011000 M
1!
#178
0!
#179
b10 9
b1 8
b1011001 M
1!
#180
0!
#181
b11 9
1*
b10 8
b1011010 M
1!
#182
0!
#183
b11 3
b11 <
b11 E
b100 2
b100 ;
b100 D
b100 9
1&
b1 %
b1 :
0*
b11 8
b1011011 M
1!
#184
0!
#185
b110 3
b110 <
b110 E
b111 2
b111 ;
b111 D
b101 9
b0 %
b0 :
0&
b100 8
b111 L
b11111111111111111111111110111010 K
b1011100 M
1!
#186
0!
#187
b1000 3
b1000 <
b1000 E
b110 9
b10 %
b10 :
1+
1,
b101 8
b111 -
b111 B
b111 J
b11111111111111111111111110111010 .
b11111111111111111111111110111010 C
b11111111111111111111111110111010 I
b11 L
b100 K
b1011101 M
1!
#188
0!
#189
b110 3
b110 <
b110 E
b111 9
b0 %
b0 :
0+
0,
b11111111111111111111111110110011 #
b11111111111111111111111110110011 =
b11111111111111111111111110110011 F
b11111111111111111111111110110011 0
b11111111111111111111111110111010 7
b110 8
b11 -
b11 B
b11 J
b100 .
b100 C
b100 I
b0 L
b1011110 M
1!
#190
0!
#191
b100 2
b100 ;
b100 D
b0 /
b0 9
1&
1)
1'
1$
b111 8
b0 -
b0 B
b0 J
b11 L
b1011111 M
1!
#192
0!
#193
b1 2
b1 ;
b1 D
b1 9
0)
0'
0&
0$
b11 /
b0 3
b0 <
b0 E
b0 1
b0 8
b11 -
b11 B
b11 J
b1100000 M
1!
#194
0!
#195
b10 9
b1 8
b1100001 M
1!
#196
0!
#197
b11 9
1*
b10 8
b1100010 M
1!
#198
0!
#199
b11 3
b11 <
b11 E
b100 2
b100 ;
b100 D
b100 9
1&
b1 %
b1 :
0*
b11 8
b1100011 M
1!
#200
0!
#201
b0 3
b0 <
b0 E
b1 2
b1 ;
b1 D
b101 9
b0 %
b0 :
0&
b100 8
b111 L
b11111111111111111111111110110011 K
b1100100 M
1!
#202
0!
#203
b10 3
b10 <
b10 E
b110 9
b10 %
b10 :
1+
1,
b101 8
b111 -
b111 B
b111 J
b11111111111111111111111110110011 .
b11111111111111111111111110110011 C
b11111111111111111111111110110011 I
b11 L
b100 K
b1100101 M
1!
#204
0!
#205
b0 3
b0 <
b0 E
b111 9
b0 %
b0 :
0+
0,
b11111111111111111111111110101100 #
b11111111111111111111111110101100 =
b11111111111111111111111110101100 F
b11111111111111111111111110101100 0
b11111111111111111111111110110011 7
b110 8
b11 -
b11 B
b11 J
b100 .
b100 C
b100 I
b110 L
b1100110 M
1!
#206
0!
#207
b100 2
b100 ;
b100 D
b110 /
b0 9
1&
1)
1'
1$
b111 8
b110 -
b110 B
b110 J
b11 L
b1100111 M
1!
#208
0!
#209
b111 2
b111 ;
b111 D
b1 9
0)
0'
0&
0$
b1001 /
b110 3
b110 <
b110 E
b110 1
b0 8
b11 -
b11 B
b11 J
b1101000 M
1!
#210
0!
#211
b10 9
b1 8
b1101001 M
1!
#212
0!
#213
b11 9
1*
b10 8
b1101010 M
1!
#214
0!
#215
b11 3
b11 <
b11 E
b100 2
b100 ;
b100 D
b100 9
1&
b1 %
b1 :
0*
b11 8
b1101011 M
1!
#216
0!
#217
b110 3
b110 <
b110 E
b111 2
b111 ;
b111 D
b101 9
b0 %
b0 :
0&
b100 8
b111 L
b11111111111111111111111110101100 K
b1101100 M
1!
#218
0!
#219
b1000 3
b1000 <
b1000 E
b110 9
b10 %
b10 :
1+
1,
b101 8
b111 -
b111 B
b111 J
b11111111111111111111111110101100 .
b11111111111111111111111110101100 C
b11111111111111111111111110101100 I
b11 L
b100 K
b1101101 M
1!
#220
0!
#221
b110 3
b110 <
b110 E
b111 9
b0 %
b0 :
0+
0,
b11111111111111111111111110100101 #
b11111111111111111111111110100101 =
b11111111111111111111111110100101 F
b11111111111111111111111110100101 0
b11111111111111111111111110101100 7
b110 8
b11 -
b11 B
b11 J
b100 .
b100 C
b100 I
b0 L
b1101110 M
1!
#222
0!
#223
b100 2
b100 ;
b100 D
b0 /
b0 9
1&
1)
1'
1$
b111 8
b0 -
b0 B
b0 J
b11 L
b1101111 M
1!
#224
0!
#225
b1 2
b1 ;
b1 D
b1 9
0)
0'
0&
0$
b11 /
b0 3
b0 <
b0 E
b0 1
b0 8
b11 -
b11 B
b11 J
b1110000 M
1!
#226
0!
#227
b10 9
b1 8
b1110001 M
1!
#228
0!
#229
b11 9
1*
b10 8
b1110010 M
1!
#230
0!
#231
b11 3
b11 <
b11 E
b100 2
b100 ;
b100 D
b100 9
1&
b1 %
b1 :
0*
b11 8
b1110011 M
1!
#232
0!
